Metadata-Version: 1.1
Name: Face-rec
Version: 0.15
Summary: Python face recognition library
Home-page: https://github.com/SOUHARDYAADHIKARY1999/Face_rec_pip
Author: SOUHARDYA ADHIKARY
Author-email: souhardyaadhikary86942@gmail.com
License: MIT
Download-URL: https://github.com/SOUHARDYAADHIKARY1999/Face_rec_pip/archive/refs/tags/v_0.15.tar.gz
Keywords: FACE,RECOGNITION,PERSONALITIES
Platform: UNKNOWN
Classifier: Development Status :: 3 - Alpha
Classifier: Intended Audience :: Developers
Classifier: Topic :: Software Development :: Build Tools
Classifier: License :: OSI Approved :: MIT License
Classifier: Programming Language :: Python :: 3.6
Classifier: Programming Language :: Python :: 3.7
